ar/__init__.py
ar/ardrive.py
ar/arweave_lib.py
ar/block.py
ar/bundle.py
ar/chunk.py
ar/manifest.py
ar/multipeer.py
ar/peer.py
ar/stream.py
ar/transaction.py
ar/wallet.py
ar/utils/__init__.py
ar/utils/ans104_signers.py
ar/utils/deep_hash.py
ar/utils/file_io.py
ar/utils/merkle.py
ar/utils/serialization.py
ar/utils/transaction_uploader.py
bundlr/__init__.py
bundlr/loader.py
bundlr/node.py
PyArweave-0.6.0.dist-info/LICENSE
PyArweave-0.6.0.dist-info/LICENSE_e142b89
PyArweave-0.6.0.dist-info/METADATA
PyArweave-0.6.0.dist-info/WHEEL
PyArweave-0.6.0.dist-info/top_level.txt
PyArweave-0.6.0.dist-info/RECORD
