Metadata-Version: 2.1
Name: PyArweave
Version: 0.6.0
Summary: Tiny Arweave Library
Home-page: https://github.com/xloem/pyarweave
Author: xloem
Keywords: arweave,crypto
Classifier: Programming Language :: Python :: 3
Classifier: License :: OSI Approved :: GNU General Public License v2 or later (GPLv2+)
Classifier: Operating System :: OS Independent
License-File: LICENSE
License-File: LICENSE_e142b89
Requires-Dist: arrow
Requires-Dist: python-jose
Requires-Dist: pycryptodome
Requires-Dist: requests
Requires-Dist: erlang-py
